alquitable/__init__.py
alquitable/__version__.py
alquitable/advanced_losses.py
alquitable/callbacks.py
alquitable/generator.py
alquitable/layers.py
alquitable/losses.py
alquitable-0.0.4.dist-info/LICENSE
alquitable-0.0.4.dist-info/METADATA
alquitable-0.0.4.dist-info/WHEEL
alquitable-0.0.4.dist-info/RECORD
