Metadata-Version: 2.1
Name: alquitable
Version: 0.0.4
Summary: Keras-core based tools to enhance Alquimodelia
Home-page: https://github.com/alquimodelia/alquitable
License: LICENSE
Keywords: python,machine learning,modeling,keras
Author: João Santos
Author-email: jotaflame@gmail.com
Requires-Python: >=3.9,<4.0
Classifier: License :: Other/Proprietary License
Classifier: Programming Language :: Python :: 3
Classifier: Programming Language :: Python :: 3.9
Classifier: Programming Language :: Python :: 3.10
Classifier: Programming Language :: Python :: 3.11
Classifier: Programming Language :: Python :: 3.12
Provides-Extra: jax
Provides-Extra: tensorflow
Provides-Extra: torch
Requires-Dist: jax ; extra == "jax"
Requires-Dist: keras (>=3)
Requires-Dist: numpy
Requires-Dist: pandas
Requires-Dist: pytorch ; extra == "torch"
Requires-Dist: tensorflow ; extra == "tensorflow"
Project-URL: Bug Tracker, https://github.com/alquimodelia/alquitable/issues
Project-URL: Documentation, https://alquimodelia.github.io/alquitable/
Project-URL: Repository, https://github.com/alquimodelia/alquitable
Project-URL: Source Code, https://github.com/alquimodelia/alquitable
